ethronsoft/__init__.py
ethronsoft/gcspypi/__init__.py
ethronsoft/gcspypi/__main__.py
ethronsoft/gcspypi/exceptions/__init__.py
ethronsoft/gcspypi/exceptions/boundary_errors.py
ethronsoft/gcspypi/exceptions/repository_errors.py
ethronsoft/gcspypi/exceptions/script_errors.py
ethronsoft/gcspypi/exceptions/state_errors.py
ethronsoft/gcspypi/package/__init__.py
ethronsoft/gcspypi/package/package.py
ethronsoft/gcspypi/package/package_builder.py
ethronsoft/gcspypi/package/package_manager.py
ethronsoft/gcspypi/parsers/__init__.py
ethronsoft/gcspypi/parsers/backup.py
ethronsoft/gcspypi/parsers/commons.py
ethronsoft/gcspypi/parsers/download.py
ethronsoft/gcspypi/parsers/install.py
ethronsoft/gcspypi/parsers/list.py
ethronsoft/gcspypi/parsers/remove.py
ethronsoft/gcspypi/parsers/search.py
ethronsoft/gcspypi/parsers/syntax.py
ethronsoft/gcspypi/parsers/uninstall.py
ethronsoft/gcspypi/parsers/upload.py
ethronsoft/gcspypi/repository/__init__.py
ethronsoft/gcspypi/repository/gcloud_remote.py
ethronsoft/gcspypi/repository/object_metadata.py
ethronsoft/gcspypi/utilities/__init__.py
ethronsoft/gcspypi/utilities/console.py
ethronsoft/gcspypi/utilities/queries.py
ethronsoft/gcspypi/utilities/version.py
test/__init__.py
test/__init__.pyc
test/console_test.py
test/console_test.pyc
test/package_builder_test.py
test/package_builder_test.pyc
test/package_manager_test.py
test/package_manager_test.pyc
test/package_test.py
test/package_test.pyc
test/repository_test.py
test/repository_test.pyc
test/utils_test.py
test/utils_test.pyc
test/__pycache__/__init__.cpython-37.pyc
test/__pycache__/console_test.cpython-37.pyc
test/__pycache__/package_builder_test.cpython-37.pyc
test/__pycache__/package_manager_test.cpython-37.pyc
test/__pycache__/package_test.cpython-37.pyc
test/__pycache__/repository_test.cpython-37.pyc
test/__pycache__/utils_test.cpython-37.pyc
test/data/WRONG-test_package-1.0.0-py2-none-any.whl
test/data/WRONG-test_package-1.0.0.zip
test/data/__init__.py
test/data/__init__.pyc
gcspypi2-1.0.10.dist-info/LICENSE
gcspypi2-1.0.10.dist-info/METADATA
gcspypi2-1.0.10.dist-info/WHEEL
gcspypi2-1.0.10.dist-info/entry_points.txt
gcspypi2-1.0.10.dist-info/top_level.txt
gcspypi2-1.0.10.dist-info/RECORD
