Metadata-Version: 2.1
Name: gcspypi2
Version: 1.0.10
Summary: Private packages repository backed by Google Cloud Storage
Home-page: https://bitbucket.org/crashtest-security/gcspypi
Author: Crashtest-Security
Author-email: manuel@crashtest-security.com
License: BSD 2-Clause License
Requires-Dist: tqdm
Requires-Dist: colorama
Requires-Dist: six (==1.11.0)
Requires-Dist: google-cloud-storage (==1.5.0)
